build_send_email/__init__.py
build_send_email/__main__.py
build_send_email/backends.py
build_send_email/config.py
build_send_email/send-email-config.yaml
build_send_email/utils.py
build_send_email-0.0.1.dist-info/entry_points.txt
build_send_email-0.0.1.dist-info/LICENSE
build_send_email-0.0.1.dist-info/WHEEL
build_send_email-0.0.1.dist-info/METADATA
build_send_email-0.0.1.dist-info/RECORD
